Workbook
Name Aporte: App!$D$13
Name Patrimonio: App!$D$16
Name Percentual: App!$D$9
Name Qtde_Anos: App!$D$14
Name Rendimento: App!$D$8
Name Salario: App!$D$7
Name Taxa_Mensal: App!$D$15
Name Valor: App!$D$10

Sheet App
B6: Ajustes
B7: Salário (R$) | D7: 4000
B8: Rendimento (%) | D8: 0.006
B9: Percentual investido (%) | D9: 0.2
B10: Valor a ser investido (R$) | D10: =IF($D$7="","",$D$7*$D$9) -> 800
B12: Aporte Mensal
B13: Investimento mensal (R$) | D13: =Valor -> 800
B14: Quantidade de anos | D14: 2
B15: Rendimento mensal (%) | D15: 0.0104
B16: Patrimônio acumulado (R$) | D16: =FV(Taxa_Mensal,Qtde_Anos*12,Aporte*-1) -> 21681.426
B17: Dividendos mensais (R$) | D17: =Patrimonio*Rendimento -> 130.08856
B19: Cenários | C19: Patrimônio | D19: Dividendos
A20: 2 | B20: Quanto em 2 anos? | C20: =FV(Taxa_Mensal,$A20*12,Aporte*-1) -> 21681.426 | D20: =$C20*Rendimento -> 130.08856
A21: 5 | B21: Quanto em 5 anos? | C21: =FV(Taxa_Mensal,$A21*12,Aporte*-1) -> 66182.613 | D21: =$C21*Rendimento -> 397.09568
A22: 10 | B22: Quanto em 10 anos? | C22: =FV(Taxa_Mensal,$A22*12,Aporte*-1) -> 189307.02 | D22: =$C22*Rendimento -> 1135.8421
A23: 20 | B23: Quanto em 20 anos? | C23: =FV(Taxa_Mensal,$A23*12,Aporte*-1) -> 844496.97 | D23: =$C23*Rendimento -> 5066.9818
A24: 30 | B24: Quanto em 30 anos? | C24: =FV(Taxa_Mensal,$A24*12,Aporte*-1) -> 3112103.7 | D24: =$C24*Rendimento -> 18672.622
B26: Perfil | D26: Ousado
B27: Valor a ser investido (R$) | D27: =Aporte -> 800
B29: Tipo de Fundo | C29: % Sugerido | D29: Valor
B30: PAPEL | C30: =VLOOKUP($D$26&"-"&$B30,Auxiliar!$A:$D,4,FALSE) -> 0.5 | D30: =C30*$D$27 -> 400
B31: TIJOLO | C31: =VLOOKUP($D$26&"-"&$B31,Auxiliar!$A:$D,4,FALSE) -> 0.1 | D31: =C31*$D$27 -> 80
B32: HÍBRIDOS | C32: =VLOOKUP($D$26&"-"&$B32,Auxiliar!$A:$D,4,FALSE) -> 0.05 | D32: =C32*$D$27 -> 40
B33: FOFs | C33: =VLOOKUP($D$26&"-"&$B33,Auxiliar!$A:$D,4,FALSE) -> 0.05 | D33: =C33*$D$27 -> 40
B34: DESENVOLVIMENTO | C34: =VLOOKUP($D$26&"-"&$B34,Auxiliar!$A:$D,4,FALSE) -> 0.2 | D34: =C34*$D$27 -> 160
B35: HOTELARIAS | C35: =VLOOKUP($D$26&"-"&$B35,Auxiliar!$A:$D,4,FALSE) -> 0.1 | D35: =C35*$D$27 -> 80
B36: Totalizador | D36: =SUM(D30:D35) -> 800

Sheet Auxiliar
A2: CHAVE | B2: PERFIL | C2: TIPO DE FII | D2: %
A3: Conservador-PAPEL | B3: Conservador | C3: PAPEL | D3: 0.3
A4: Conservador-TIJOLO | B4: Conservador | C4: TIJOLO | D4: 0.5
A5: Conservador-HÍBRIDOS | B5: Conservador | C5: HÍBRIDOS | D5: 0.1
A6: Conservador-FOFs | B6: Conservador | C6: FOFs | D6: 0.1
A7: Conservador-DESENVOLVIMENTO | B7: Conservador | C7: DESENVOLVIMENTO | D7: 0
A8: Conservador-HOTELARIAS | B8: Conservador | C8: HOTELARIAS | D8: 0
A9: Moderado-PAPEL | B9: Moderado | C9: PAPEL | D9: 0.32
A10: Moderado-TIJOLO | B10: Moderado | C10: TIJOLO | D10: 0.35
A11: Moderado-HÍBRIDOS | B11: Moderado | C11: HÍBRIDOS | D11: 0.08
A12: Moderado-FOFs | B12: Moderado | C12: FOFs | D12: 0.05
A13: Moderado-DESENVOLVIMENTO | B13: Moderado | C13: DESENVOLVIMENTO | D13: 0.1
A14: Moderado-HOTELARIAS | B14: Moderado | C14: HOTELARIAS | D14: 0.1
... A20: Ousado-HOTELARIAS | B20: Ousado | C20: HOTELARIAS | D20: 0.1
